{
  "fabric:load_conditions": [
    {
      "condition": "assortedlib:part_enabled",
      "part": "painting"
    }
  ],
  "parent": "minecraft:recipes/root",
  "criteria": {
    "has_tar": {
      "conditions": {
        "items": [
          {
            "tag": "c:tar"
          }
        ]
      },
      "trigger": "minecraft:inventory_changed"
    },
    "has_the_recipe": {
      "conditions": {
        "recipe": "assorteddecor:siding_horizontal_brown"
      },
      "trigger": "minecraft:recipe_unlocked"
    }
  },
  "requirements": [
    [
      "has_tar",
      "has_the_recipe"
    ]
  ],
  "rewards": {
    "recipes": [
      "assorteddecor:siding_horizontal_brown"
    ]
  },
  "sends_telemetry_event": true
}